asgardeo/__init__.py
asgardeo/auth/__init__.py
asgardeo/auth/client.py
asgardeo/auth/util.py
asgardeo/models.py
asgardeo-0.2.1.dist-info/METADATA
asgardeo-0.2.1.dist-info/WHEEL
asgardeo-0.2.1.dist-info/RECORD
