Metadata-Version: 2.3
Name: asgardeo
Version: 0.2.1
Summary: Python SDK for Asgardeo
License: MIT
Author: Thilina Senarath
Author-email: thilinas@wso2.com
Requires-Python: >=3.10,<4.0
Classifier: License :: OSI Approved :: MIT License
Classifier: Programming Language :: Python :: 3
Classifier: Programming Language :: Python :: 3.10
Classifier: Programming Language :: Python :: 3.11
Classifier: Programming Language :: Python :: 3.12
Classifier: Programming Language :: Python :: 3.13
Requires-Dist: httpx (>=0.28.0,<0.29.0)
